spimple/__init__.py
spimple/fits.py
spimple/utils.py
spimple/apps/__init__.py
spimple/apps/image_convolver.py
spimple/apps/mosaic.py
spimple/apps/power_beam_maker.py
spimple/apps/spi_fitter.py
spimple-0.0.5.dist-info/METADATA
spimple-0.0.5.dist-info/WHEEL
spimple-0.0.5.dist-info/entry_points.txt
spimple-0.0.5.dist-info/licenses/LICENSE
spimple-0.0.5.dist-info/RECORD
