Metadata-Version: 2.4
Name: spimple
Version: 0.0.5
Summary: Radio astronomy image post-processing tools
Project-URL: Homepage, https://github.com/landmanbester/spimple
Author-email: Landman Bester <lbester@sarao.ac.za>
License: MIT
License-File: LICENSE
Classifier: License :: OSI Approved :: MIT License
Classifier: Operating System :: OS Independent
Classifier: Programming Language :: Python :: 3
Requires-Python: <3.13,>=3.10
Requires-Dist: codex-africanus[complete]
Requires-Dist: dask-ms[xarray]>=0.2.22
Requires-Dist: dask[array]<=2024.10
Requires-Dist: katbeam
Requires-Dist: omegaconf
Requires-Dist: pyscilog>=0.1.2
Requires-Dist: ray[default]
Requires-Dist: reproject
Provides-Extra: dev
Requires-Dist: pytest>=8.0.0; extra == 'dev'
Requires-Dist: tbump>=6.11.0; extra == 'dev'
